libusb1.py
usb1/__init__.py
usb1/_libusb1.py
usb1/_version.py
usb1/libusb1.py
usb1/testUSB1.py
usb1/__pyinstaller/__init__.py
usb1/__pyinstaller/hook-usb1.py
usb1/__pyinstaller/test_libusb1_packaging.py
libusb1-2.0.0.dist-info/COPYING
libusb1-2.0.0.dist-info/COPYING.LESSER
libusb1-2.0.0.dist-info/METADATA
libusb1-2.0.0.dist-info/WHEEL
libusb1-2.0.0.dist-info/entry_points.txt
libusb1-2.0.0.dist-info/top_level.txt
libusb1-2.0.0.dist-info/RECORD
