Metadata-Version: 1.1
Name: libusb1
Version: 2.0.0
Summary: Pure-python wrapper for libusb-1.0
Home-page: http://github.com/vpelletier/python-libusb1
Author: Vincent Pelletier
Author-email: plr.vincent@gmail.com
License: LGPLv2.1+
Keywords: usb libusb
Platform: any
Classifier: Intended Audience :: Developers
Classifier: License :: OSI Approved :: GNU Lesser General Public License v2 or later (LGPLv2+)
Classifier: Operating System :: OS Independent
Classifier: Programming Language :: Python :: 3
Classifier: Programming Language :: Python :: 3.4
Classifier: Programming Language :: Python :: 3.5
Classifier: Programming Language :: Python :: 3.6
Classifier: Programming Language :: Python :: 3.7
Classifier: Programming Language :: Python :: Implementation :: CPython
Classifier: Programming Language :: Python :: Implementation :: PyPy
Classifier: Topic :: Software Development :: Libraries
Classifier: Topic :: System :: Hardware :: Hardware Drivers
